stataconf/__init__.py
stataconf/sops-v3.8.1.linux.amd64
stataconf-0.1.3.dist-info/LICENSE
stataconf-0.1.3.dist-info/METADATA
stataconf-0.1.3.dist-info/WHEEL
stataconf-0.1.3.dist-info/top_level.txt
stataconf-0.1.3.dist-info/RECORD
