Metadata-Version: 2.1
Name: stataconf
Version: 0.1.3
Author-email: Bastien GANDOUET <bastien@mozaiqu.es>
License: The MIT License (MIT)
Classifier: License :: OSI Approved :: MIT License
Requires-Python: >=3.11
License-File: LICENSE
Requires-Dist: smart-open[s3] <7.0.0,>=6.0.0
